silverriver/__init__.py
silverriver/cli.py
silverriver/client/__init__.py
silverriver/client/agent_endpoints.py
silverriver/client/browser_endpoints.py
silverriver/client/endpoint.py
silverriver/client/http_client.py
silverriver/golden_paths/__init__.py
silverriver/golden_paths/record_golden_draft.py
silverriver/interfaces/__init__.py
silverriver/interfaces/base_agent.py
silverriver/interfaces/chat.py
silverriver/interfaces/data_models.py
silverriver/utils/__init__.py
silverriver/utils/execution.py
silverriver/utils/remote_browser.py
silverriver-0.1.36.dist-info/METADATA
silverriver-0.1.36.dist-info/WHEEL
silverriver-0.1.36.dist-info/entry_points.txt
silverriver-0.1.36.dist-info/top_level.txt
silverriver-0.1.36.dist-info/RECORD
